README.txt
setup.cfg
setup.py
doc/Makefile
doc/make.bat
doc/source/ChangeLog.rst
doc/source/conf.py
doc/source/index.rst
doc/source/quickstart.rst
doc/source/references.rst
src/rtools/.Rhistory
src/rtools/__init__.py
src/rtools/colormap.py
src/rtools/error.py
src/rtools/init.py
src/rtools/package.py
src/rtools/plots.py
src/rtools/s4.py
src/rtools/tools.py
src/rtools.egg-info/PKG-INFO
src/rtools.egg-info/SOURCES.txt
src/rtools.egg-info/dependency_links.txt
src/rtools.egg-info/requires.txt
src/rtools.egg-info/top_level.txt
src/rtools.egg-info/zip-safe
test/test_colormap.py
test/test_error.py
test/test_package.py
test/test_plots.py
test/test_s4.py
test/test_tools.py