Metadata-Version: 1.0
Name: rtools
Version: 0.2.11
Summary: utilities to ease manipulation of R packages using rpy2.
Home-page: ['http://pypi.python.org/pypi/rtools']
Author: Thomas Cokelaer
Author-email: cokelaer@ebi.ac.uk
License: GPL
Download-URL: ['http://pypi.python.org/pypi/rtools']
Keywords: rpy2,R
Platform: Linux
Platform: Unix
Platform: MacOsX
Platform: Windows
Classifier: Development Status :: 5 - Production/Stable
Classifier: Intended Audience :: Developers
Classifier: Intended Audience :: Science/Research
Classifier: License :: OSI Approved :: GNU Library or Lesser General Public License (LGPL)
Classifier: Operating System :: OS Independent
Classifier: Programming Language :: Python :: 2.7
Classifier: Topic :: Software Development :: Libraries :: Python Modules
Classifier: Topic :: Scientific/Engineering :: Bio-Informatics
Classifier: Topic :: Scientific/Engineering :: Information Analysis
Classifier: Topic :: Scientific/Engineering :: Mathematics
Classifier: Topic :: Scientific/Engineering :: Physics
